microdaemon/__init__.py
microdaemon/abstracts.py
microdaemon/channels.py
microdaemon/common.py
microdaemon/configclass.py
microdaemon/configurator.py
microdaemon/jsonlib.py
microdaemon/runner.py
microdaemon/threads.py
microdaemon/database/__init__.py
microdaemon/database/datatype.py
microdaemon/database/models.py
microdaemon/server/__init__.py
microdaemon/server/decorators.py
microdaemon/server/exceptions.py
microdaemon/server/pages.py
microdaemon/server/request.py
microdaemon/server/responses.py
microdaemon/server/server.py
microdaemon-0.1.5.dist-info/LICENSE
microdaemon-0.1.5.dist-info/METADATA
microdaemon-0.1.5.dist-info/WHEEL
microdaemon-0.1.5.dist-info/top_level.txt
microdaemon-0.1.5.dist-info/RECORD
