Metadata-Version: 2.1
Name: microdaemon
Version: 0.1.5
Summary: A small framework for python services
Home-page: https://github.com/chiara-paci/microdaemon
Author: Chiara Paci
Author-email: chiara.paci@gmail.com
License: UNKNOWN
Platform: UNKNOWN
Classifier: Development Status :: 3 - Alpha
Classifier: Programming Language :: Python :: 3
Classifier: Operating System :: POSIX :: Linux
Classifier: Intended Audience :: Developers
Classifier: License :: OSI Approved :: GNU General Public License v3 or later (GPLv3+)
Classifier: Topic :: Software Development :: Libraries :: Application Frameworks
Requires-Dist: Jinja2
Requires-Dist: eventlet
Requires-Dist: exifread
Requires-Dist: numpy
Requires-Dist: pandas
Requires-Dist: python-magic
Requires-Dist: python-prctl
Requires-Dist: pytz
Requires-Dist: socketio
Requires-Dist: wheel
